cinemagoer-2022.12.27.data/scripts/get_company.py
cinemagoer-2022.12.27.data/scripts/get_first_company.py
cinemagoer-2022.12.27.data/scripts/get_first_movie.py
cinemagoer-2022.12.27.data/scripts/get_first_person.py
cinemagoer-2022.12.27.data/scripts/get_keyword.py
cinemagoer-2022.12.27.data/scripts/get_movie.py
cinemagoer-2022.12.27.data/scripts/get_movie_list.py
cinemagoer-2022.12.27.data/scripts/get_person.py
cinemagoer-2022.12.27.data/scripts/get_top_bottom_movies.py
cinemagoer-2022.12.27.data/scripts/imdbpy2sql.py
cinemagoer-2022.12.27.data/scripts/s32cinemagoer.py
cinemagoer-2022.12.27.data/scripts/search_company.py
cinemagoer-2022.12.27.data/scripts/search_keyword.py
cinemagoer-2022.12.27.data/scripts/search_movie.py
cinemagoer-2022.12.27.data/scripts/search_person.py
imdb/Character.py
imdb/Company.py
imdb/Movie.py
imdb/Person.py
imdb/__init__.py
imdb/_exceptions.py
imdb/_logging.py
imdb/cli.py
imdb/helpers.py
imdb/linguistics.py
imdb/utils.py
imdb/version.py
imdb/locale/__init__.py
imdb/locale/imdbpy-ar.po
imdb/locale/imdbpy-bg.po
imdb/locale/imdbpy-de.po
imdb/locale/imdbpy-en.po
imdb/locale/imdbpy-es.po
imdb/locale/imdbpy-fr.po
imdb/locale/imdbpy-it.po
imdb/locale/imdbpy-pt_BR.po
imdb/locale/imdbpy-sr.po
imdb/locale/imdbpy-tr.po
imdb/locale/imdbpy.pot
imdb/locale/ar/LC_MESSAGES/imdbpy.mo
imdb/locale/bg/LC_MESSAGES/imdbpy.mo
imdb/locale/de/LC_MESSAGES/imdbpy.mo
imdb/locale/en/LC_MESSAGES/imdbpy.mo
imdb/locale/es/LC_MESSAGES/imdbpy.mo
imdb/locale/fr/LC_MESSAGES/imdbpy.mo
imdb/locale/it/LC_MESSAGES/imdbpy.mo
imdb/locale/pt_BR/LC_MESSAGES/imdbpy.mo
imdb/locale/sr/LC_MESSAGES/imdbpy.mo
imdb/locale/tr/LC_MESSAGES/imdbpy.mo
imdb/parser/__init__.py
imdb/parser/logging.py
imdb/parser/http/__init__.py
imdb/parser/http/companyParser.py
imdb/parser/http/listParser.py
imdb/parser/http/logging.py
imdb/parser/http/movieParser.py
imdb/parser/http/personParser.py
imdb/parser/http/piculet.py
imdb/parser/http/searchCompanyParser.py
imdb/parser/http/searchKeywordParser.py
cinemagoer-2022.12.27.dist-info/LICENSE.txt
cinemagoer-2022.12.27.dist-info/METADATA
cinemagoer-2022.12.27.dist-info/WHEEL
cinemagoer-2022.12.27.dist-info/entry_points.txt
cinemagoer-2022.12.27.dist-info/top_level.txt
cinemagoer-2022.12.27.dist-info/RECORD
