Metadata-Version: 2.1
Name: cinemagoer
Version: 2022.12.27
Summary: Python package to access the IMDb's database
Home-page: https://cinemagoer.github.io/
Author: Davide Alberani
Author-email: da@mimante.net
Maintainer: Davide Alberani
Maintainer-email: da@mimante.net
License: GPL
Download-URL: https://cinemagoer.github.io/downloads/
Project-URL: Source, https://github.com/cinemagoer/cinemagoer
Keywords: imdb,movie,people,database,cinema,film,person,cast,actor,actress,director,sql,character,company,package,plain text data files,keywords,top250,bottom100,xml
Platform: any
Classifier: Development Status :: 5 - Production/Stable
Classifier: Environment :: Console
Classifier: Environment :: Web Environment
Classifier: Intended Audience :: Developers
Classifier: Intended Audience :: End Users/Desktop
Classifier: License :: OSI Approved :: GNU General Public License (GPL)
Classifier: Natural Language :: English
Classifier: Natural Language :: Italian
Classifier: Natural Language :: Turkish
Classifier: Programming Language :: Python
Classifier: Programming Language :: Python :: 3.11
Classifier: Programming Language :: Python :: 3.10
Classifier: Programming Language :: Python :: 3.9
Classifier: Programming Language :: Python :: 3.8
Classifier: Programming Language :: Python :: 3.7
Classifier: Programming Language :: Python :: 3.6
Classifier: Programming Language :: Python :: 3.5
Classifier: Programming Language :: Python :: 2.7
Classifier: Programming Language :: Python :: Implementation :: CPython
Classifier: Programming Language :: Python :: Implementation :: PyPy
Classifier: Operating System :: OS Independent
Classifier: Topic :: Database :: Front-Ends
Classifier: Topic :: Internet :: WWW/HTTP :: Dynamic Content :: CGI Tools/Libraries
Classifier: Topic :: Software Development :: Libraries :: Python Modules
Provides-Extra: dev
Provides-Extra: doc
License-File: LICENSE.txt
